mat3ra/__init__.py
mat3ra/esse/__init__.py
mat3ra/esse/utils.py
mat3ra/esse/data/__init__.py
mat3ra/esse/data/examples.py
mat3ra/esse/data/properties.py
mat3ra/esse/data/schemas.py
mat3ra/esse/models/__init__.py
mat3ra/esse/models/context_provider.py
mat3ra/esse/models/element.py
mat3ra/esse/models/project.py
mat3ra/esse/models/apse/db/__init__.py
mat3ra/esse/models/apse/db/third_party_sources.py
mat3ra/esse/models/apse/db/materials_project/2025_9.25/__init__.py
mat3ra/esse/models/apse/db/materials_project/2025_9.25/summary.py
mat3ra/esse/models/apse/db/materials_project/legacy/__init__.py
mat3ra/esse/models/apse/db/materials_project/legacy/material.py
mat3ra/esse/models/apse/db/nist_jarvis/2024_3.13/__init__.py
mat3ra/esse/models/apse/db/nist_jarvis/2024_3.13/atoms.py
mat3ra/esse/models/apse/db/nist_jarvis/2024_3.13/db_entry.py
mat3ra/esse/models/apse/file/applications/espresso/7.2/__init__.py
mat3ra/esse/models/apse/file/applications/espresso/7.2/pw_x.py
mat3ra/esse/models/apse/file/applications/espresso/7.2/pw.x/__init__.py
mat3ra/esse/models/apse/file/applications/espresso/7.2/pw.x/atomic_positions.py
mat3ra/esse/models/apse/file/applications/espresso/7.2/pw.x/atomic_species.py
mat3ra/esse/models/apse/file/applications/espresso/7.2/pw.x/cell.py
mat3ra/esse/models/apse/file/applications/espresso/7.2/pw.x/cell_parameters.py
mat3ra/esse/models/apse/file/applications/espresso/7.2/pw.x/control.py
mat3ra/esse/models/apse/file/applications/espresso/7.2/pw.x/electrons.py
mat3ra/esse/models/apse/file/applications/espresso/7.2/pw.x/hubbard.py
mat3ra/esse/models/apse/file/applications/espresso/7.2/pw.x/ions.py
mat3ra/esse/models/apse/file/applications/espresso/7.2/pw.x/k_points.py
mat3ra/esse/models/apse/file/applications/espresso/7.2/pw.x/system.py
mat3ra/esse/models/apse/materials/builders/slab/pymatgen/__init__.py
mat3ra/esse/models/apse/materials/builders/slab/pymatgen/parameters.py
mat3ra/esse/models/apse/materials/materials_project/__init__.py
mat3ra_esse-2025.12.16.post0.dist-info/licenses/LICENSE.md
mat3ra_esse-2025.12.16.post0.dist-info/METADATA
mat3ra_esse-2025.12.16.post0.dist-info/WHEEL
mat3ra_esse-2025.12.16.post0.dist-info/top_level.txt
mat3ra_esse-2025.12.16.post0.dist-info/RECORD
