Metadata-Version: 2.4
Name: mat3ra-esse
Version: 2025.12.16.post0
Summary: Excellent Source of Schemas and Examples.
Author-email: "Exabyte Inc." <info@mat3ra.com>
License: # LICENSE
Classifier: Programming Language :: Python
Classifier: Programming Language :: Python :: 3
Classifier: Development Status :: 3 - Alpha
Classifier: Topic :: Software Development
Requires-Python: >=3.10
License-File: LICENSE.md
Requires-Dist: exabyte-json-include>=2023.12.23.post0
Requires-Dist: jsonschema>=2.6.0
Provides-Extra: dev
Requires-Dist: datamodel-code-generator==0.28.5; extra == "dev"
Requires-Dist: pre-commit>=4.1.0; extra == "dev"
Provides-Extra: tests
Requires-Dist: coverage[toml]>=5.3; extra == "tests"
Requires-Dist: parameterized>=0.9.0; extra == "tests"
Provides-Extra: all
Requires-Dist: mat3ra-esse[dev,tests]; extra == "all"
Dynamic: license-file
